cocoutils/__init__.py
cocoutils/analyzer.py
cocoutils/checker.py
cocoutils/drwaUtils.py
cocoutils/transfer.py
cocoutils/utils.py
cocoutils_cv-0.0.2.dist-info/LICENSE
cocoutils_cv-0.0.2.dist-info/METADATA
cocoutils_cv-0.0.2.dist-info/WHEEL
cocoutils_cv-0.0.2.dist-info/top_level.txt
cocoutils_cv-0.0.2.dist-info/RECORD
