Metadata-Version: 2.1
Name: cocoutils-cv
Version: 0.0.2
Summary: Microsoft COCO data set transformation analysis utils
Home-page: https://github.com/Rayson2020-8/cocodataset-utils
Author: RaysonShi
Author-email: raysonshi@qq.com
License: MIT Licence
Classifier: Programming Language :: Python :: 3
Classifier: License :: OSI Approved :: MIT License
Classifier: Operating System :: OS Independent
License-File: LICENSE
Requires-Dist: numpy
Requires-Dist: pycocotools
Requires-Dist: matplotlib
Requires-Dist: tqdm
Requires-Dist: opencv-python
